{"name":"AvalonEdit","tagline":"The WPF-based text editor component used in SharpDevelop","body":"### AvalonEdit\r\nAvalonEdit is a WPF-based text editor component. It was written by @dgrunwald for the SharpDevelop IDE.\r\nVersion 5 of AvalonEdit is released under the MIT license.\r\n\r\n![AvalonEdit Screenshot](http://www.codeproject.com/KB/edit/AvalonEdit/screenshot.png)\r\n\r\n### Documentation\r\n\r\nFor introductory documentation, please take a look at the CodeProject article \"[Using AvalonEdit](http://www.codeproject.com/KB/edit/AvalonEdit.aspx)\"\r\n\r\nThe source code download of AvalonEdit contains sources for a help file (created with Sandcastle, if you don't like reading the XML sources). The compiled help file is available as download on the CodeProject article.\r\n\r\n### Download\r\nPre-built AvalonEdit binaries are available in the `ICSharpCode.AvalonEdit` NuGet package. The package contains binaries for .NET 3.5 and .NET 4.x.\r\n\r\nThe source code is available on GitHub.","google":"","note":"Don't delete this file! It's used internally to help with page regeneration."}